{
  "_class": "group",
  "do_objectID": "62FE1B6F-8FA9-46B4-A239-25804C4F68D2",
  "exportOptions": {
    "_class": "exportOptions",
    "exportFormats": [
    ],
    "includedLayerIds": [
    ],
    "layerOptions": 0,
    "shouldTrim": false
  },
  "frame": {
    "_class": "rect",
    "constrainProportions": false,
    "height": 50,
    "width": 280,
    "x": 232,
    "y": 0
  },
  "hasClickThrough": false,
  "isFlippedHorizontal": false,
  "isFlippedVertical": false,
  "isLocked": false,
  "isVisible": true,
  "layerListExpandedType": 0,
  "layers": [
    {
      "class": "shapeGroup",
      "id": "D11C33B8-64EE-4F98-B6C0-EAF3348A65C5"
    },
    {
      "class": "text",
      "id": "3814BB65-2848-47A8-8AF7-AA54527FB5AC"
    }
  ],
  "name": "Input / Text (Error)",
  "nameIsFixed": false,
  "originalObjectID": "62FE1B6F-8FA9-46B4-A239-25804C4F68D2",
  "resizingConstraint": 63,
  "resizingType": 0,
  "rotation": 0,
  "shouldBreakMaskChain": false,
  "style": {
    "_class": "style",
    "endDecorationType": 0,
    "miterLimit": 10,
    "startDecorationType": 0
  },
  "userInfo": {
    "com.animaapp.stc-sketch-plugin": {
      "kModelPropertiesKey": {
        "constraints": {
          "automatic": 1,
          "left": {
            "constant": 232,
            "enabled": 1,
            "modelID": "constraint_198fa193-9b74-49fd-b572-246de5f3fb93",
            "model_class": "ADModelConstraint",
            "model_version": 0.1,
            "multiplier": 0
          },
          "modelID": "viewConstraints_2b1a6770-1a7a-4d8c-9e0c-6c54e594938d",
          "model_class": "ADModelViewConstraints",
          "model_version": 0.1,
          "right": {
            "constant": 0,
            "enabled": 1,
            "modelID": "constraint_1ca8bb85-745d-44dd-8d6c-2976898f7d9e",
            "model_class": "ADModelConstraint",
            "model_version": 0.1,
            "multiplier": 0
          },
          "scaleFactor": 1
        }
      }
    }
  }
}