{
  "_class": "shapeGroup",
  "clippingMaskMode": 0,
  "do_objectID": "73604029-6685-404E-8213-445F24A48531",
  "exportOptions": {
    "_class": "exportOptions",
    "exportFormats": [
    ],
    "includedLayerIds": [
    ],
    "layerOptions": 0,
    "shouldTrim": false
  },
  "frame": {
    "_class": "rect",
    "constrainProportions": false,
    "height": 215,
    "width": 320,
    "x": 0,
    "y": 0
  },
  "hasClickThrough": false,
  "hasClippingMask": false,
  "isFlippedHorizontal": false,
  "isFlippedVertical": false,
  "isLocked": false,
  "isVisible": true,
  "layerListExpandedType": 0,
  "layers": [
    {
      "class": "rectangle",
      "id": "E46744E3-0464-4F7A-9EE0-34918C64D7A7"
    }
  ],
  "name": "Rectangle 2",
  "nameIsFixed": false,
  "originalObjectID": "73604029-6685-404E-8213-445F24A48531",
  "resizingConstraint": 63,
  "resizingType": 0,
  "rotation": 0,
  "shouldBreakMaskChain": false,
  "style": {
    "sharedObjectID": "A8D3D5EC-BCC5-40DE-A1DF-306B2EB4FB74"
  },
  "userInfo": {
    "com.animaapp.stc-sketch-plugin": {
      "kModelPropertiesKey": {
      }
    }
  },
  "windingRule": 1
}