{
  "_class": "shapePath",
  "booleanOperation": -1,
  "do_objectID": "C5EDA72E-C445-4ABE-A23F-982261DE3BFF",
  "edited": true,
  "exportOptions": {
    "_class": "exportOptions",
    "exportFormats": [
    ],
    "includedLayerIds": [
    ],
    "layerOptions": 0,
    "shouldTrim": false
  },
  "frame": {
    "_class": "rect",
    "constrainProportions": false,
    "height": 6.899749999999997,
    "width": 6.898833333333333,
    "x": 0,
    "y": 0
  },
  "isFlippedHorizontal": false,
  "isFlippedVertical": false,
  "isLocked": false,
  "isVisible": true,
  "layerListExpandedType": 0,
  "name": "Path",
  "nameIsFixed": false,
  "path": {
    "_class": "path",
    "isClosed": true,
    "pointRadiusBehaviour": 1,
    "points": [
      {
        "_class": "curvePoint",
        "cornerRadius": 0,
        "curveFrom": "{1, 0.77613923209778157}",
        "curveMode": 2,
        "curveTo": "{1, 0.22386076790221895}",
        "hasCurveFrom": true,
        "hasCurveTo": true,
        "point": "{1, 0.49993357247243275}"
      },
      {
        "_class": "curvePoint",
        "cornerRadius": 0,
        "curveFrom": "{0.22375764018070704, 1}",
        "curveMode": 2,
        "curveTo": "{0.77610948711134753, 1}",
        "hasCurveFrom": true,
        "hasCurveTo": true,
        "point": "{0.49986712729205429, 1}"
      },
      {
        "_class": "curvePoint",
        "cornerRadius": 0,
        "curveFrom": "{0, 0.22386076790221895}",
        "curveMode": 2,
        "curveTo": "{0, 0.77613923209778157}",
        "hasCurveFrom": true,
        "hasCurveTo": true,
        "point": "{0, 0.49993357247243275}"
      },
      {
        "_class": "curvePoint",
        "cornerRadius": 0,
        "curveFrom": "{0.77610948711134753, 0}",
        "curveMode": 2,
        "curveTo": "{0.22375764018070704, 0}",
        "hasCurveFrom": true,
        "hasCurveTo": true,
        "point": "{0.49986712729205429, 0}"
      }
    ]
  },
  "resizingConstraint": 63,
  "resizingType": 0,
  "rotation": 0,
  "shouldBreakMaskChain": false
}