{
  "_class": "shapePath",
  "booleanOperation": -1,
  "do_objectID": "D02A825D-2AFB-4E9A-B839-59E5B254D0A1",
  "edited": true,
  "exportOptions": {
    "_class": "exportOptions",
    "exportFormats": [
    ],
    "includedLayerIds": [
    ],
    "layerOptions": 0,
    "shouldTrim": false
  },
  "frame": {
    "_class": "rect",
    "constrainProportions": false,
    "height": 4.784931506849315,
    "width": 4.836712328767121,
    "x": 1.351095890410958,
    "y": 1.334794520547947
  },
  "isFlippedHorizontal": false,
  "isFlippedVertical": false,
  "isLocked": false,
  "isVisible": true,
  "layerListExpandedType": 0,
  "name": "Path",
  "nameIsFixed": false,
  "path": {
    "_class": "path",
    "isClosed": false,
    "pointRadiusBehaviour": 1,
    "points": [
      {
        "_class": "curvePoint",
        "cornerRadius": 0,
        "curveFrom": "{0.22422680412371152, 0}",
        "curveMode": 4,
        "curveTo": "{0.5, 0}",
        "hasCurveFrom": true,
        "hasCurveTo": false,
        "point": "{0.5, 0}"
      },
      {
        "_class": "curvePoint",
        "cornerRadius": 0,
        "curveFrom": "{0, 0.77575150300601214}",
        "curveMode": 2,
        "curveTo": "{0, 0.22424849699398783}",
        "hasCurveFrom": true,
        "hasCurveTo": true,
        "point": "{0, 0.49999999999999928}"
      },
      {
        "_class": "curvePoint",
        "cornerRadius": 0,
        "curveFrom": "{0.77577319587628846, 1}",
        "curveMode": 2,
        "curveTo": "{0.22422680412371152, 1}",
        "hasCurveFrom": true,
        "hasCurveTo": true,
        "point": "{0.5, 1}"
      },
      {
        "_class": "curvePoint",
        "cornerRadius": 0,
        "curveFrom": "{1, 0.22424849699398783}",
        "curveMode": 2,
        "curveTo": "{1, 0.77575150300601214}",
        "hasCurveFrom": true,
        "hasCurveTo": true,
        "point": "{1, 0.49999999999999928}"
      },
      {
        "_class": "curvePoint",
        "cornerRadius": 0,
        "curveFrom": "{0.5, 0}",
        "curveMode": 4,
        "curveTo": "{0.77577319587628846, 0}",
        "hasCurveFrom": false,
        "hasCurveTo": true,
        "point": "{0.5, 0}"
      }
    ]
  },
  "resizingConstraint": 63,
  "resizingType": 0,
  "rotation": 0,
  "shouldBreakMaskChain": false
}