{
  "_class": "shapeGroup",
  "clippingMaskMode": 0,
  "do_objectID": "C3F9C335-5192-4D64-A28B-26DB52B7F63D",
  "exportOptions": {
    "_class": "exportOptions",
    "exportFormats": [
    ],
    "includedLayerIds": [
    ],
    "layerOptions": 0,
    "shouldTrim": false
  },
  "frame": {
    "_class": "rect",
    "constrainProportions": false,
    "height": 11.77302857142857,
    "width": 24.66500571428652,
    "x": 7.360731428570944,
    "y": 8.57062857142864
  },
  "hasClickThrough": false,
  "hasClippingMask": false,
  "isFlippedHorizontal": false,
  "isFlippedVertical": false,
  "isLocked": false,
  "isVisible": true,
  "layerListExpandedType": 0,
  "layers": [
    {
      "class": "shapePath",
      "id": "A4923B18-889F-43AC-9398-9F787BAF1669"
    },
    {
      "class": "shapePath",
      "id": "16E710BE-FB78-495E-A800-A4B4503854FA"
    },
    {
      "class": "shapePath",
      "id": "3EF1E1C0-7BEF-4092-A5DF-4E791B94989B"
    }
  ],
  "name": "Combined Shape",
  "nameIsFixed": false,
  "originalObjectID": "C3F9C335-5192-4D64-A28B-26DB52B7F63D",
  "resizingConstraint": 63,
  "resizingType": 0,
  "rotation": 0,
  "shouldBreakMaskChain": false,
  "style": {
    "_class": "style",
    "endDecorationType": 0,
    "fills": [
      {
        "_class": "fill",
        "color": {
          "_class": "color",
          "alpha": 1,
          "blue": 0.596,
          "green": 0.314,
          "red": 0
        },
        "fillType": 0,
        "isEnabled": true,
        "noiseIndex": 0,
        "noiseIntensity": 0,
        "patternFillType": 1,
        "patternTileScale": 1
      }
    ],
    "miterLimit": 10,
    "startDecorationType": 0
  },
  "userInfo": {
    "com.animaapp.stc-sketch-plugin": {
      "kModelPropertiesKey": {
      }
    }
  },
  "windingRule": 1
}