{
  "_class": "group",
  "do_objectID": "9BD03C14-90DF-4A6A-AC24-0E56DD0FD1ED",
  "exportOptions": {
    "_class": "exportOptions",
    "exportFormats": [
    ],
    "includedLayerIds": [
    ],
    "layerOptions": 0,
    "shouldTrim": false
  },
  "frame": {
    "_class": "rect",
    "constrainProportions": false,
    "height": 68,
    "width": 290,
    "x": 15,
    "y": 67
  },
  "hasClickThrough": false,
  "isFlippedHorizontal": false,
  "isFlippedVertical": false,
  "isLocked": false,
  "isVisible": true,
  "layerListExpandedType": 0,
  "layers": [
    {
      "class": "symbolInstance",
      "id": "B902BAC1-755A-4CC4-A39A-854712348DF5"
    },
    {
      "class": "text",
      "id": "880C4761-F60F-4730-8A38-05CCB3A29854"
    }
  ],
  "name": "Stacked Group",
  "nameIsFixed": false,
  "resizingConstraint": 63,
  "resizingType": 0,
  "rotation": 0,
  "shouldBreakMaskChain": false,
  "style": {
    "_class": "style",
    "endDecorationType": 0,
    "miterLimit": 10,
    "startDecorationType": 0
  },
  "userInfo": {
    "com.animaapp.stc-sketch-plugin": {
      "kModelPropertiesKey": {
        "align": 2,
        "constraints": {
          "automatic": 1,
          "left": {
            "constant": 15,
            "enabled": 1,
            "modelID": "constraint_011789f6-e90a-4caa-a37e-cdb117498113",
            "model_class": "ADModelConstraint",
            "model_version": 0.1,
            "multiplier": 0
          },
          "modelID": "viewConstraints_b31bd761-d48d-42bd-b4c3-023bb71d2d28",
          "model_class": "ADModelViewConstraints",
          "model_version": 0.1,
          "right": {
            "constant": 15,
            "enabled": 1,
            "modelID": "constraint_a5341a70-3ca7-4e25-b1bb-17be952fe8e2",
            "model_class": "ADModelConstraint",
            "model_version": 0.1,
            "multiplier": 0
          },
          "scaleFactor": 1
        },
        "isCollapsing": 1,
        "spacing": 10,
        "type": 0
      },
      "kViewTypeKey": "ADModelStackView"
    }
  }
}