{
  "_class": "group",
  "do_objectID": "76FDAB85-4FCE-4604-B4A9-8BBCA99DAF5E",
  "exportOptions": {
    "_class": "exportOptions",
    "exportFormats": [
    ],
    "includedLayerIds": [
    ],
    "layerOptions": 0,
    "shouldTrim": false
  },
  "frame": {
    "_class": "rect",
    "constrainProportions": false,
    "height": 18,
    "width": 32,
    "x": 0,
    "y": 0
  },
  "hasClickThrough": false,
  "isFlippedHorizontal": false,
  "isFlippedVertical": false,
  "isLocked": false,
  "isVisible": true,
  "layerListExpandedType": 2,
  "layers": [
    {
      "class": "shapeGroup",
      "id": "BBD21AAD-A773-4D2E-9864-04209318B4FD"
    },
    {
      "class": "text",
      "id": "70851B4D-8829-4338-8EC3-E12E9570A153"
    }
  ],
  "name": "Dynamic group",
  "nameIsFixed": false,
  "originalObjectID": "76FDAB85-4FCE-4604-B4A9-8BBCA99DAF5E",
  "resizingConstraint": 63,
  "resizingType": 0,
  "rotation": 0,
  "shouldBreakMaskChain": false,
  "style": {
    "_class": "style",
    "endDecorationType": 0,
    "miterLimit": 10,
    "startDecorationType": 0
  },
  "userInfo": {
    "com.animaapp.stc-sketch-plugin": {
      "kModelPropertiesKey": {
      }
    }
  }
}