{
  "_class": "group",
  "do_objectID": "9207CB3A-D4E7-474D-BD0C-AA941B613D5A",
  "exportOptions": {
    "_class": "exportOptions",
    "exportFormats": [
    ],
    "includedLayerIds": [
    ],
    "layerOptions": 0,
    "shouldTrim": false
  },
  "frame": {
    "_class": "rect",
    "constrainProportions": false,
    "height": 256,
    "width": 473,
    "x": 0,
    "y": 0
  },
  "hasClickThrough": false,
  "isFlippedHorizontal": false,
  "isFlippedVertical": false,
  "isLocked": false,
  "isVisible": true,
  "layerListExpandedType": 0,
  "layers": [
    {
      "class": "shapeGroup",
      "id": "34442026-CCC2-4D4B-A87D-309D8D08F94E"
    },
    {
      "class": "symbolInstance",
      "id": "7BC87CDA-F3CF-41E6-B26E-301448C38365"
    },
    {
      "class": "bitmap",
      "id": "B1C357C5-1F18-4956-BB81-E04467055A5E"
    },
    {
      "class": "text",
      "id": "B452A5AA-9CC5-45C2-AE13-AC9D398D0A6D"
    },
    {
      "class": "text",
      "id": "76E3F7FE-F9E3-41BA-A006-BB21E4361E34"
    },
    {
      "class": "text",
      "id": "095B61B6-FCA6-4743-A10F-D93D36F41416"
    },
    {
      "class": "text",
      "id": "864314AD-0207-4237-8865-98425540876F"
    },
    {
      "class": "symbolInstance",
      "id": "54EE38DB-8C29-4DF7-86F2-24F100FA403B"
    }
  ],
  "name": "Group 2",
  "nameIsFixed": false,
  "originalObjectID": "9207CB3A-D4E7-474D-BD0C-AA941B613D5A",
  "resizingConstraint": 63,
  "resizingType": 0,
  "rotation": 0,
  "shouldBreakMaskChain": false,
  "style": {
    "_class": "style",
    "endDecorationType": 0,
    "miterLimit": 10,
    "startDecorationType": 0
  },
  "userInfo": {
    "com.animaapp.stc-sketch-plugin": {
      "kModelPropertiesKey": {
      }
    }
  }
}