{
  "_class": "group",
  "do_objectID": "26D25084-675F-4799-9F16-C406FDA13107",
  "exportOptions": {
    "_class": "exportOptions",
    "exportFormats": [
    ],
    "includedLayerIds": [
    ],
    "layerOptions": 0,
    "shouldTrim": false
  },
  "frame": {
    "_class": "rect",
    "constrainProportions": false,
    "height": 16,
    "width": 15,
    "x": 1,
    "y": 2
  },
  "hasClickThrough": false,
  "isFlippedHorizontal": false,
  "isFlippedVertical": false,
  "isLocked": false,
  "isVisible": true,
  "layerListExpandedType": 0,
  "layers": [
    {
      "class": "shapeGroup",
      "id": "BB56F44D-845E-4327-9D3F-D3BDA1A8CBD5"
    },
    {
      "class": "symbolInstance",
      "id": "C3CCAD27-0968-47D8-A62E-1C5940445D4A"
    }
  ],
  "name": "Link small",
  "nameIsFixed": true,
  "originalObjectID": "26D25084-675F-4799-9F16-C406FDA13107",
  "resizingConstraint": 63,
  "resizingType": 0,
  "rotation": 0,
  "shouldBreakMaskChain": false,
  "style": {
    "_class": "style",
    "endDecorationType": 0,
    "miterLimit": 10,
    "startDecorationType": 0
  },
  "userInfo": {
    "com.animaapp.stc-sketch-plugin": {
      "kModelPropertiesKey": {
      }
    }
  }
}